psrdb/__init__.py
psrdb/data/l_band_gain_calibrators.csv
psrdb/data/molonglo_phasing.txt
psrdb/data/polarisation_calibrators.csv
psrdb/data/s_band_gain_calibrators.csv
psrdb/data/uhf_band_gain_calibrators.csv
psrdb/graphql_client.py
psrdb/graphql_table.py
psrdb/load_data.py
psrdb/scripts/__init__.py
psrdb/scripts/generate_meerkat_json.py
psrdb/scripts/generate_molonglo_json.py
psrdb/scripts/ingest_obs.py
psrdb/scripts/psrdb.py
psrdb/tables/__init__.py
psrdb/tables/calibration.py
psrdb/tables/ephemeris.py
psrdb/tables/main_project.py
psrdb/tables/observation.py
psrdb/tables/pipeline_image.py
psrdb/tables/pipeline_run.py
psrdb/tables/project.py
psrdb/tables/pulsar.py
psrdb/tables/pulsar_fold_result.py
psrdb/tables/pulsar_fold_summary.py
psrdb/tables/residual.py
psrdb/tables/telescope.py
psrdb/tables/template.py
psrdb/tables/toa.py
psrdb/utils/__init__.py
psrdb/utils/ephemeris.py
psrdb/utils/header.py
psrdb/utils/other.py
psrdb/utils/residual.py
psrdb/utils/toa.py
psrdb/utils/upload.py
psrdb-3.0.6.dist-info/LICENSE
psrdb-3.0.6.dist-info/METADATA
psrdb-3.0.6.dist-info/WHEEL
psrdb-3.0.6.dist-info/entry_points.txt
psrdb-3.0.6.dist-info/RECORD
