Metadata-Version: 2.1
Name: psrdb
Version: 3.0.6
Summary: CLI for pulsars.org.au
License: MIT
Author: GWDC
Requires-Python: >=3.9,<4.0
Classifier: License :: OSI Approved :: MIT License
Classifier: Programming Language :: Python :: 3
Classifier: Programming Language :: Python :: 3.9
Classifier: Programming Language :: Python :: 3.10
Classifier: Programming Language :: Python :: 3.11
Requires-Dist: pulsar-paragraph (>=1.0.1,<2.0.0)
Requires-Dist: python-decouple (>=3.8,<4.0)
Requires-Dist: requests (>=2.25.1,<3.0.0)
